rule_engine/__init__.py
rule_engine/py.typed
rule_engine/rule.py
rule_engine/tests/__init__.py
rule_engine/tests/test_rule_engine.py
rule_engine/tests/test_utils.py
rule_engine/utils.py
light_rule_engine-1.2.0.dist-info/LICENSE
light_rule_engine-1.2.0.dist-info/METADATA
light_rule_engine-1.2.0.dist-info/WHEEL
light_rule_engine-1.2.0.dist-info/RECORD
