Metadata-Version: 2.3
Name: light-rule-engine
Version: 1.2.0
Summary: A simple rule engine
License: MIT
Author: Biagio Distefano
Author-email: me@biagiodistefano.io
Requires-Python: >=3.10,<4.0
Classifier: License :: OSI Approved :: MIT License
Classifier: Programming Language :: Python :: 3
Classifier: Programming Language :: Python :: 3.10
Classifier: Programming Language :: Python :: 3.11
Classifier: Programming Language :: Python :: 3.12
Classifier: Programming Language :: Python :: 3.13
